l2_data_utils/__init__.py
l2_data_utils/services/__init__.py
l2_data_utils/services/pipelines/__init__.py
l2_data_utils/services/pipelines/incremental_pipeline_functions.py
l2_data_utils/services/transformations/__init__.py
l2_data_utils/services/transformations/dataset_transformation.py
l2_data_utils/services/transformations/utils.py
l2_data_utils-1.1.3.dist-info/METADATA
l2_data_utils-1.1.3.dist-info/WHEEL
l2_data_utils-1.1.3.dist-info/top_level.txt
l2_data_utils-1.1.3.dist-info/RECORD
