Metadata-Version: 2.1
Name: l2-data-utils
Version: 1.1.3
Summary: UNKNOWN
Home-page: UNKNOWN
License: UNKNOWN
Platform: UNKNOWN
Requires-Dist: pyspark
Requires-Dist: delta-spark
